quoter/__init__.py
quoter/base.py
quoter/joiner.py
quoter/markdown.py
quoter/quoter.py
quoter/styleset.py
quoter/util.py
quoter/version.py
quoter/xmlhtml.py
quoter-1.6.8.dist-info/DESCRIPTION.rst
quoter-1.6.8.dist-info/METADATA
quoter-1.6.8.dist-info/RECORD
quoter-1.6.8.dist-info/WHEEL
quoter-1.6.8.dist-info/metadata.json
quoter-1.6.8.dist-info/top_level.txt
