Metadata-Version: 2.0
Name: quoter
Version: 1.6.8
Summary: Powerful way to construct text, HTML, and XML, plus a kick-ass join
Home-page: https://bitbucket.org/jeunice/quoter
Author: Jonathan Eunice
Author-email: jonathan.eunice@gmail.com
License: Apache License 2.0
Keywords: quote wrap prefix suffix endcap repr representation html xml join
Platform: UNKNOWN
Classifier: Development Status :: 4 - Beta
Classifier: Operating System :: OS Independent
Classifier: License :: OSI Approved :: Apache Software License
Classifier: Intended Audience :: Developers
Classifier: Programming Language :: Python
Classifier: Programming Language :: Python :: 2
Classifier: Programming Language :: Python :: 2.7
Classifier: Programming Language :: Python :: 3
Classifier: Programming Language :: Python :: 3.2
Classifier: Programming Language :: Python :: 3.3
Classifier: Programming Language :: Python :: 3.4
Classifier: Programming Language :: Python :: 3.5
Classifier: Programming Language :: Python :: 3.6
Classifier: Programming Language :: Python :: Implementation :: CPython
Classifier: Programming Language :: Python :: Implementation :: PyPy
Classifier: Topic :: Software Development :: Libraries :: Python Modules
Classifier: Topic :: Text Processing :: Filters
Classifier: Topic :: Text Processing :: Markup
Classifier: Topic :: Text Processing :: Markup :: HTML
Classifier: Topic :: Text Processing :: Markup :: XML
Requires-Dist: options (>=1.4.6)
Requires-Dist: six (>=1.10)
